coherent/test/__init__.py
coherent/test/core.py
coherent/test/monkey.py
coherent/test/__main__.py
coherent_test-0.8.1.dist-info/METADATA
coherent_test-0.8.1.dist-info/WHEEL
coherent_test-0.8.1.dist-info/entry_points.txt
coherent_test-0.8.1.dist-info/RECORD
