Metadata-Version: 2.3
Name: coherent.test
Version: 0.8.1
Author-Email: "Jason R. Coombs" <jaraco@jaraco.com>
Summary: Run tests for Coherent projects.
Requires-Python: >= 3.8
Requires-Dist: pytest
Requires-Dist: pytest-enabler
Requires-Dist: pytest-ruff
Requires-Dist: pip-run
Requires-Dist: coherent.build
Requires-Dist: jaraco.compat
Provides-Extra: doc
Provides-Extra: test
Project-URL: Source, https://github.com/coherent-oss/coherent.test
Classifier: Development Status :: 4 - Beta
Classifier: Intended Audience :: Developers
Classifier: License :: OSI Approved :: MIT License
Classifier: Programming Language :: Python :: 3
Classifier: Programming Language :: Python :: 3 :: Only
